DESCRIPTION.rst
MANIFEST.in
README.rst
setup.py
hs_restclient/__init__.py
hs_restclient/compat.py
hs_restclient/exceptions.py
hs_restclient/generators.py
hs_restclient/util.py
hs_restclient.egg-info/PKG-INFO
hs_restclient.egg-info/SOURCES.txt
hs_restclient.egg-info/dependency_links.txt
hs_restclient.egg-info/requires.txt
hs_restclient.egg-info/top_level.txt
hs_restclient/endpoints/__init__.py
hs_restclient/endpoints/resources.py