Metadata-Version: 1.1
Name: hs-restclient
Version: 1.2.11
Summary: HydroShare REST API client library
Home-page: https://github.com/hydroshare/hs_restclient
Author: HydroShare
Author-email: brian_miles@unc.edu
License: BSD
Keywords: hydroinformatics hydrology reproducible science
Platform: UNKNOWN
Classifier: Development Status :: 5 - Production/Stable
Classifier: Intended Audience :: Developers
Classifier: Topic :: Scientific/Engineering
Classifier: Topic :: Software Development :: Libraries :: Python Modules
Classifier: License :: OSI Approved :: BSD License
Classifier: Programming Language :: Python :: 2.7
